robotframework_interpreter/__init__.py
robotframework_interpreter/constants.py
robotframework_interpreter/interpreter.py
robotframework_interpreter/listeners.py
robotframework_interpreter/robot_version.py
robotframework_interpreter/selectors.py
robotframework_interpreter/selectors_pywin32.py
robotframework_interpreter/selectors_white.py
robotframework_interpreter/utils.py
robotframework_interpreter/resources/simmerjs/LICENSE
robotframework_interpreter/resources/simmerjs/simmer.js
robotframework_interpreter-0.7.6.dist-info/LICENSE
robotframework_interpreter-0.7.6.dist-info/METADATA
robotframework_interpreter-0.7.6.dist-info/WHEEL
robotframework_interpreter-0.7.6.dist-info/top_level.txt
robotframework_interpreter-0.7.6.dist-info/RECORD
